SpringBoot25KaifaShizhan/README.md
SpringBoot25KaifaShizhan/__init__.py
SpringBoot25KaifaShizhan/__main__.py
SpringBoot25KaifaShizhan/file.pdf
SpringBoot25KaifaShizhan/index.html
spring_boot_2_5_kaifa_shizhan-2024.3.6.0.dist-info/METADATA
spring_boot_2_5_kaifa_shizhan-2024.3.6.0.dist-info/WHEEL
spring_boot_2_5_kaifa_shizhan-2024.3.6.0.dist-info/entry_points.txt
spring_boot_2_5_kaifa_shizhan-2024.3.6.0.dist-info/top_level.txt
spring_boot_2_5_kaifa_shizhan-2024.3.6.0.dist-info/RECORD
